jsonlint/__init__.py
jsonlint/compat.py
jsonlint/fields.py
jsonlint/i18n.py
jsonlint/jsons.py
jsonlint/meta.py
jsonlint/utils.py
jsonlint/validators.py
jsonlint/locale/wtforms.pot
jsonlint/locale/ar/LC_MESSAGES/wtforms.mo
jsonlint/locale/ar/LC_MESSAGES/wtforms.po
jsonlint/locale/ca/LC_MESSAGES/wtforms.mo
jsonlint/locale/ca/LC_MESSAGES/wtforms.po
jsonlint/locale/cs_CZ/LC_MESSAGES/wtforms.mo
jsonlint/locale/cs_CZ/LC_MESSAGES/wtforms.po
jsonlint/locale/cy/LC_MESSAGES/wtforms.mo
jsonlint/locale/cy/LC_MESSAGES/wtforms.po
jsonlint/locale/de/LC_MESSAGES/wtforms.mo
jsonlint/locale/de/LC_MESSAGES/wtforms.po
jsonlint/locale/de_CH/LC_MESSAGES/wtforms.mo
jsonlint/locale/de_CH/LC_MESSAGES/wtforms.po
jsonlint/locale/el/LC_MESSAGES/wtforms.mo
jsonlint/locale/el/LC_MESSAGES/wtforms.po
jsonlint/locale/en/LC_MESSAGES/wtforms.mo
jsonlint/locale/en/LC_MESSAGES/wtforms.po
jsonlint/locale/es/LC_MESSAGES/wtforms.mo
jsonlint/locale/es/LC_MESSAGES/wtforms.po
jsonlint/locale/et/LC_MESSAGES/wtforms.mo
jsonlint/locale/et/LC_MESSAGES/wtforms.po
jsonlint/locale/fa/LC_MESSAGES/wtforms.mo
jsonlint/locale/fa/LC_MESSAGES/wtforms.po
jsonlint/locale/fi/LC_MESSAGES/wtforms.po
jsonlint/locale/fr/LC_MESSAGES/wtforms.mo
jsonlint/locale/fr/LC_MESSAGES/wtforms.po
jsonlint/locale/hu/LC_MESSAGES/wtforms.mo
jsonlint/locale/hu/LC_MESSAGES/wtforms.po
jsonlint/locale/it/LC_MESSAGES/wtforms.mo
jsonlint/locale/it/LC_MESSAGES/wtforms.po
jsonlint/locale/ja/LC_MESSAGES/wtforms.mo
jsonlint/locale/ja/LC_MESSAGES/wtforms.po
jsonlint/locale/ko/LC_MESSAGES/wtforms.mo
jsonlint/locale/ko/LC_MESSAGES/wtforms.po
jsonlint/locale/nb/LC_MESSAGES/wtforms.mo
jsonlint/locale/nb/LC_MESSAGES/wtforms.po
jsonlint/locale/nl/LC_MESSAGES/wtforms.mo
jsonlint/locale/nl/LC_MESSAGES/wtforms.po
jsonlint/locale/pl/LC_MESSAGES/wtforms.mo
jsonlint/locale/pl/LC_MESSAGES/wtforms.po
jsonlint/locale/pt/LC_MESSAGES/wtforms.mo
jsonlint/locale/pt/LC_MESSAGES/wtforms.po
jsonlint-0.1.dist-info/DESCRIPTION.rst
jsonlint-0.1.dist-info/METADATA
jsonlint-0.1.dist-info/RECORD
jsonlint-0.1.dist-info/WHEEL
jsonlint-0.1.dist-info/metadata.json
jsonlint-0.1.dist-info/top_level.txt
